acme_demo_widget/__init__.py
acme_demo_widget/core.py
petercort_demo_widget-0.1.0.post20251208194605.dist-info/METADATA
petercort_demo_widget-0.1.0.post20251208194605.dist-info/WHEEL
petercort_demo_widget-0.1.0.post20251208194605.dist-info/entry_points.txt
petercort_demo_widget-0.1.0.post20251208194605.dist-info/top_level.txt
petercort_demo_widget-0.1.0.post20251208194605.dist-info/RECORD
