Metadata-Version: 2.4
Name: petercort-demo-widget
Version: 0.1.0.post20251208194605
Summary: A tiny demo package for internal PyPI registry testing
Author-email: Internal Dev <dev@example.com>
License-Expression: MIT
Project-URL: Homepage, https://example.com/internal-pypi
Keywords: demo,pypi,internal
Classifier: Programming Language :: Python :: 3
Classifier: Operating System :: OS Independent
Requires-Python: >=3.8
